[
    {
        "url":  "https://api.github.com/repos/nervosnetwork/fiber/releases/assets/292364562",
        "id":  292364562,
        "node_id":  "RA_kwDOLfBvi84RbSES",
        "name":  "fnn_v0.6.0-rc5-x86_64-darwin-portable.tar.gz",
        "label":  "",
        "uploader":  {
                         "login":  "github-actions[bot]",
                         "id":  41898282,
                         "node_id":  "MDM6Qm90NDE4OTgyODI=",
                         "avatar_url":  "https://avatars.githubusercontent.com/in/15368?v=4",
                         "gravatar_id":  "",
                         "url":  "https://api.github.com/users/github-actions%5Bbot%5D",
                         "html_url":  "https://github.com/apps/github-actions",
                         "followers_url":  "https://api.github.com/users/github-actions%5Bbot%5D/followers",
                         "following_url":  "https://api.github.com/users/github-actions%5Bbot%5D/following{/other_user}",
                         "gists_url":  "https://api.github.com/users/github-actions%5Bbot%5D/gists{/gist_id}",
                         "starred_url":  "https://api.github.com/users/github-actions%5Bbot%5D/starred{/owner}{/repo}",
                         "subscriptions_url":  "https://api.github.com/users/github-actions%5Bbot%5D/subscriptions",
                         "organizations_url":  "https://api.github.com/users/github-actions%5Bbot%5D/orgs",
                         "repos_url":  "https://api.github.com/users/github-actions%5Bbot%5D/repos",
                         "events_url":  "https://api.github.com/users/github-actions%5Bbot%5D/events{/privacy}",
                         "received_events_url":  "https://api.github.com/users/github-actions%5Bbot%5D/received_events",
                         "type":  "Bot",
                         "user_view_type":  "public",
                         "site_admin":  false
                     },
        "content_type":  "application/gzip",
        "state":  "uploaded",
        "size":  24710807,
        "digest":  "sha256:7fdfa64c8b5bc981cd07383f928031bd23d9edcfd9f428cabe27bc3027adbaaf",
        "download_count":  6,
        "created_at":  "2025-09-12T02:11:31Z",
        "updated_at":  "2025-09-12T02:11:32Z",
        "browser_download_url":  "https://github.com/nervosnetwork/fiber/releases/download/v0.6.0-rc5/fnn_v0.6.0-rc5-x86_64-darwin-portable.tar.gz"
    },
    {
        "url":  "https://api.github.com/repos/nervosnetwork/fiber/releases/assets/292357185",
        "id":  292357185,
        "node_id":  "RA_kwDOLfBvi84RbQRB",
        "name":  "fnn_v0.6.0-rc5-x86_64-linux-portable.tar.gz",
        "label":  "",
        "uploader":  {
                         "login":  "github-actions[bot]",
                         "id":  41898282,
                         "node_id":  "MDM6Qm90NDE4OTgyODI=",
                         "avatar_url":  "https://avatars.githubusercontent.com/in/15368?v=4",
                         "gravatar_id":  "",
                         "url":  "https://api.github.com/users/github-actions%5Bbot%5D",
                         "html_url":  "https://github.com/apps/github-actions",
                         "followers_url":  "https://api.github.com/users/github-actions%5Bbot%5D/followers",
                         "following_url":  "https://api.github.com/users/github-actions%5Bbot%5D/following{/other_user}",
                         "gists_url":  "https://api.github.com/users/github-actions%5Bbot%5D/gists{/gist_id}",
                         "starred_url":  "https://api.github.com/users/github-actions%5Bbot%5D/starred{/owner}{/repo}",
                         "subscriptions_url":  "https://api.github.com/users/github-actions%5Bbot%5D/subscriptions",
                         "organizations_url":  "https://api.github.com/users/github-actions%5Bbot%5D/orgs",
                         "repos_url":  "https://api.github.com/users/github-actions%5Bbot%5D/repos",
                         "events_url":  "https://api.github.com/users/github-actions%5Bbot%5D/events{/privacy}",
                         "received_events_url":  "https://api.github.com/users/github-actions%5Bbot%5D/received_events",
                         "type":  "Bot",
                         "user_view_type":  "public",
                         "site_admin":  false
                     },
        "content_type":  "application/gzip",
        "state":  "uploaded",
        "size":  26678097,
        "digest":  "sha256:b911f6891dec96adf31de568b5f7bce79196b5c0a8850d58126a4db5decb6eb9",
        "download_count":  44,
        "created_at":  "2025-09-12T01:53:55Z",
        "updated_at":  "2025-09-12T01:53:56Z",
        "browser_download_url":  "https://github.com/nervosnetwork/fiber/releases/download/v0.6.0-rc5/fnn_v0.6.0-rc5-x86_64-linux-portable.tar.gz"
    },
    {
        "url":  "https://api.github.com/repos/nervosnetwork/fiber/releases/assets/292356503",
        "id":  292356503,
        "node_id":  "RA_kwDOLfBvi84RbQGX",
        "name":  "fnn_v0.6.0-rc5-x86_64-linux.tar.gz",
        "label":  "",
        "uploader":  {
                         "login":  "github-actions[bot]",
                         "id":  41898282,
                         "node_id":  "MDM6Qm90NDE4OTgyODI=",
                         "avatar_url":  "https://avatars.githubusercontent.com/in/15368?v=4",
                         "gravatar_id":  "",
                         "url":  "https://api.github.com/users/github-actions%5Bbot%5D",
                         "html_url":  "https://github.com/apps/github-actions",
                         "followers_url":  "https://api.github.com/users/github-actions%5Bbot%5D/followers",
                         "following_url":  "https://api.github.com/users/github-actions%5Bbot%5D/following{/other_user}",
                         "gists_url":  "https://api.github.com/users/github-actions%5Bbot%5D/gists{/gist_id}",
                         "starred_url":  "https://api.github.com/users/github-actions%5Bbot%5D/starred{/owner}{/repo}",
                         "subscriptions_url":  "https://api.github.com/users/github-actions%5Bbot%5D/subscriptions",
                         "organizations_url":  "https://api.github.com/users/github-actions%5Bbot%5D/orgs",
                         "repos_url":  "https://api.github.com/users/github-actions%5Bbot%5D/repos",
                         "events_url":  "https://api.github.com/users/github-actions%5Bbot%5D/events{/privacy}",
                         "received_events_url":  "https://api.github.com/users/github-actions%5Bbot%5D/received_events",
                         "type":  "Bot",
                         "user_view_type":  "public",
                         "site_admin":  false
                     },
        "content_type":  "application/gzip",
        "state":  "uploaded",
        "size":  26921619,
        "digest":  "sha256:206e3bc28ebb85aaceb01f4ae774685a4adf259e5c2daa7d6de12471f5564546",
        "download_count":  3,
        "created_at":  "2025-09-12T01:52:45Z",
        "updated_at":  "2025-09-12T01:52:46Z",
        "browser_download_url":  "https://github.com/nervosnetwork/fiber/releases/download/v0.6.0-rc5/fnn_v0.6.0-rc5-x86_64-linux.tar.gz"
    },
    {
        "url":  "https://api.github.com/repos/nervosnetwork/fiber/releases/assets/292364402",
        "id":  292364402,
        "node_id":  "RA_kwDOLfBvi84RbSBy",
        "name":  "fnn_v0.6.0-rc5-x86_64-windows.tar.gz",
        "label":  "",
        "uploader":  {
                         "login":  "github-actions[bot]",
                         "id":  41898282,
                         "node_id":  "MDM6Qm90NDE4OTgyODI=",
                         "avatar_url":  "https://avatars.githubusercontent.com/in/15368?v=4",
                         "gravatar_id":  "",
                         "url":  "https://api.github.com/users/github-actions%5Bbot%5D",
                         "html_url":  "https://github.com/apps/github-actions",
                         "followers_url":  "https://api.github.com/users/github-actions%5Bbot%5D/followers",
                         "following_url":  "https://api.github.com/users/github-actions%5Bbot%5D/following{/other_user}",
                         "gists_url":  "https://api.github.com/users/github-actions%5Bbot%5D/gists{/gist_id}",
                         "starred_url":  "https://api.github.com/users/github-actions%5Bbot%5D/starred{/owner}{/repo}",
                         "subscriptions_url":  "https://api.github.com/users/github-actions%5Bbot%5D/subscriptions",
                         "organizations_url":  "https://api.github.com/users/github-actions%5Bbot%5D/orgs",
                         "repos_url":  "https://api.github.com/users/github-actions%5Bbot%5D/repos",
                         "events_url":  "https://api.github.com/users/github-actions%5Bbot%5D/events{/privacy}",
                         "received_events_url":  "https://api.github.com/users/github-actions%5Bbot%5D/received_events",
                         "type":  "Bot",
                         "user_view_type":  "public",
                         "site_admin":  false
                     },
        "content_type":  "application/gzip",
        "state":  "uploaded",
        "size":  27087375,
        "digest":  "sha256:593cf83ba547057fa5ed9d5b01cb1d7f1c06625ddb6874778e0a3dfe537addea",
        "download_count":  3,
        "created_at":  "2025-09-12T02:11:00Z",
        "updated_at":  "2025-09-12T02:11:01Z",
        "browser_download_url":  "https://github.com/nervosnetwork/fiber/releases/download/v0.6.0-rc5/fnn_v0.6.0-rc5-x86_64-windows.tar.gz"
    }
]
